tyadmin_api_cli/__init__.py
tyadmin_api_cli/cmd.py
tyadmin_api_cli/contants.py
tyadmin_api_cli/deal_antd_pages.py
tyadmin_api_cli/deal_antd_route.py
tyadmin_api_cli/deal_display.py
tyadmin_api_cli/deal_xadmin.py
tyadmin_api_cli/fields.py
tyadmin_api_cli/gen_filter.py
tyadmin_api_cli/gen_one_model_all.py
tyadmin_api_cli/gen_serializer.py
tyadmin_api_cli/gen_url.py
tyadmin_api_cli/gen_view.py
tyadmin_api_cli/init_filter_serial_url_view.py
tyadmin_api_cli/ty_admin_settings.py
tyadmin_api_cli/utils.py
tyadmin_api_cli/adapters/__init__.py
tyadmin_api_cli/adapters/django_celery_beat_ty_admin.py
tyadmin_api_cli/adapters/field_adapter.py
tyadmin_api_cli/antd/__init__.py
tyadmin_api_cli/antd/constant.py
tyadmin_api_cli/antd/field.py
tyadmin_api_cli/antd_full_templates/README.md
tyadmin_api_cli/antd_full_templates/jest.config.js
tyadmin_api_cli/antd_full_templates/jsconfig.json
tyadmin_api_cli/antd_full_templates/package-lock.json
tyadmin_api_cli/antd_full_templates/package.json
tyadmin_api_cli/antd_full_templates/yarn.lock
tyadmin_api_cli/antd_full_templates/config/config.js
tyadmin_api_cli/antd_full_templates/config/defaultSettings.js
tyadmin_api_cli/antd_full_templates/config/proxy.js
tyadmin_api_cli/antd_full_templates/config/routes.js
tyadmin_api_cli/antd_full_templates/mock/listTableList.js
tyadmin_api_cli/antd_full_templates/mock/notices.js
tyadmin_api_cli/antd_full_templates/mock/route.js
tyadmin_api_cli/antd_full_templates/mock/user.js
tyadmin_api_cli/antd_full_templates/public/CNAME
tyadmin_api_cli/antd_full_templates/public/favicon.png
tyadmin_api_cli/antd_full_templates/public/home_bg.png
tyadmin_api_cli/antd_full_templates/public/pro_icon.svg
tyadmin_api_cli/antd_full_templates/public/icons/icon-128x128.png
tyadmin_api_cli/antd_full_templates/public/icons/icon-192x192.png
tyadmin_api_cli/antd_full_templates/public/icons/icon-512x512.png
tyadmin_api_cli/antd_full_templates/src/global.jsx
tyadmin_api_cli/antd_full_templates/src/global.less
tyadmin_api_cli-0.8.3.dist-info/LICENSE
tyadmin_api_cli-0.8.3.dist-info/METADATA
tyadmin_api_cli-0.8.3.dist-info/WHEEL
tyadmin_api_cli-0.8.3.dist-info/top_level.txt
tyadmin_api_cli-0.8.3.dist-info/RECORD
