Metadata-Version: 2.1
Name: tyadmin-api-cli
Version: 0.8.3
Summary: modern base on models django admin powered by Antd Design Pro
Home-page: https://github.com/mtianyan/tyadmin_api_cli
Author: mtianyan
Author-email: mtianyan@qq.com
License: MIT Licence
Keywords: pip,mtianyan,xadmin,Django,Antd,Antd Design Pro
Platform: any
License-File: LICENSE
Requires-Dist: django
Requires-Dist: django-simple-captcha
Requires-Dist: djangorestframework
Requires-Dist: django-filter
Requires-Dist: demjson3
